cloud_bids_layout/__init__.py
cloud_bids_layout/_meta.py
cloud_bids_layout/cli.py
cloud_bids_layout/cloud_bids_layout.py
cloud_bids_layout/version.py
tests/__init__.py
tests/test_cloud_bids_layout.py
cloud_bids_layout-0.1.2.dist-info/LICENSE
cloud_bids_layout-0.1.2.dist-info/METADATA
cloud_bids_layout-0.1.2.dist-info/WHEEL
cloud_bids_layout-0.1.2.dist-info/top_level.txt
cloud_bids_layout-0.1.2.dist-info/RECORD
