Metadata-Version: 2.1
Name: cloud-bids-layout
Version: 0.1.2
Summary: Cloud-BIDS-Layout: Use pybids with Amazon S3
Home-page: https://github.com/nrdg/cloud_bids_layout
Author: Adam Richie-Halford
Author-email: richiehalford@gmail.com
Maintainer: Adam Richie-Halford
Maintainer-email: richiehalford@gmail.com
License: MIT
Platform: OS Independent
Classifier: Development Status :: 3 - Alpha
Classifier: Environment :: Console
Classifier: Intended Audience :: Science/Research
Classifier: License :: OSI Approved :: MIT License
Classifier: Operating System :: OS Independent
Classifier: Natural Language :: English
Classifier: Programming Language :: Python
Classifier: Programming Language :: Python :: 3
Classifier: Programming Language :: Python :: 3.6
Classifier: Programming Language :: Python :: 3.7
Classifier: Programming Language :: Python :: 3.8
Classifier: Topic :: Scientific/Engineering
Requires-Python: >=3.6
Requires-Dist: Click (>=7.0)
Requires-Dist: boto3 (==1.14.28)
Requires-Dist: botocore (==1.17.28)
Requires-Dist: pybids (==0.11.1)
Requires-Dist: s3fs (==0.4.2)
Provides-Extra: dev
Requires-Dist: bump2version (==0.5.11) ; extra == 'dev'
Requires-Dist: Click (==7.0) ; extra == 'dev'
Requires-Dist: coverage (==4.5.4) ; extra == 'dev'
Requires-Dist: docutils (==0.15.2) ; extra == 'dev'
Requires-Dist: flake8 (==3.7.8) ; extra == 'dev'
Requires-Dist: numpydoc (==1.1.0) ; extra == 'dev'
Requires-Dist: pip (==20.1.1) ; extra == 'dev'
Requires-Dist: pytest-cov (==2.8.1) ; extra == 'dev'
Requires-Dist: pytest-runner (==5.1) ; extra == 'dev'
Requires-Dist: pytest (==5.4.3) ; extra == 'dev'
Requires-Dist: Sphinx (==1.8.5) ; extra == 'dev'
Requires-Dist: nbsphinx (==0.7.1) ; extra == 'dev'
Requires-Dist: tox (==3.17.0) ; extra == 'dev'
Requires-Dist: watchdog (==0.9.0) ; extra == 'dev'
Requires-Dist: wheel (==0.33.6) ; extra == 'dev'
Requires-Dist: moto (>=1.3.15.dev964) ; extra == 'dev'
Requires-Dist: pre-commit ; extra == 'dev'
